odoo/addons/pos_order_product_search/README.rst
odoo/addons/pos_order_product_search/__init__.py
odoo/addons/pos_order_product_search/__manifest__.py
odoo/addons/pos_order_product_search/i18n/es.po
odoo/addons/pos_order_product_search/i18n/fr.po
odoo/addons/pos_order_product_search/i18n/it.po
odoo/addons/pos_order_product_search/i18n/pos_order_product_search.pot
odoo/addons/pos_order_product_search/readme/CONTRIBUTORS.rst
odoo/addons/pos_order_product_search/readme/DESCRIPTION.rst
odoo/addons/pos_order_product_search/readme/ROADMAP.rst
odoo/addons/pos_order_product_search/readme/USAGE.rst
odoo/addons/pos_order_product_search/static/description/icon.png
odoo/addons/pos_order_product_search/static/description/index.html
odoo/addons/pos_order_product_search/views/pos.xml
odoo14_addon_pos_order_product_search-14.0.1.0.1.dev10.dist-info/METADATA
odoo14_addon_pos_order_product_search-14.0.1.0.1.dev10.dist-info/WHEEL
odoo14_addon_pos_order_product_search-14.0.1.0.1.dev10.dist-info/top_level.txt
odoo14_addon_pos_order_product_search-14.0.1.0.1.dev10.dist-info/RECORD
